Metadata-Version: 2.1
Name: lib-bas-eng
Version: 0.0.1
Summary: First Lib by BAS
Home-page: https://github.com/basketball999/lib_bas_eng
Author: BASKETBALL
Author-email: ballketball999@gmail.com
License: MIT
Download-URL: https://github.com/basketball999/lib_bas_eng/archive/v0.0.1.zip
Keywords: bas
Platform: UNKNOWN
Classifier: Development Status :: 3 - Alpha
Classifier: Intended Audience :: Education
Classifier: Topic :: Utilities
Classifier: License :: OSI Approved :: MIT License
Classifier: Programming Language :: Python :: 3
Classifier: Programming Language :: Python :: 3.4
Classifier: Programming Language :: Python :: 3.5
Classifier: Programming Language :: Python :: 3.6
Classifier: Programming Language :: Python :: 3.7
Classifier: Programming Language :: Python :: 3.8
Classifier: Programming Language :: Python :: 3.9
Classifier: Programming Language :: Python :: 3.10
License-File: LICENSE.txt
